wellcad/__init__.py
wellcad/com/__init__.py
wellcad/com/_application.py
wellcad/com/_borehole.py
wellcad/com/_comment_box.py
wellcad/com/_cross_section_box.py
wellcad/com/_depth.py
wellcad/com/_dispatch_wrapper.py
wellcad/com/_drill_item.py
wellcad/com/_equipment_item.py
wellcad/com/_font.py
wellcad/com/_fossil_item.py
wellcad/com/_header.py
wellcad/com/_interval_item.py
wellcad/com/_litho_bed.py
wellcad/com/_litho_dictionary.py
wellcad/com/_litho_pattern.py
wellcad/com/_log.py
wellcad/com/_marker_item.py
wellcad/com/_odbc.py
wellcad/com/_page.py
wellcad/com/_polar_and_rose_box.py
wellcad/com/_stacking_pattern_item.py
wellcad/com/_structure.py
wellcad/com/_title.py
wellcad/com/_workspace.py
pywellcad-0.5.0.dist-info/LICENSE.txt
pywellcad-0.5.0.dist-info/METADATA
pywellcad-0.5.0.dist-info/WHEEL
pywellcad-0.5.0.dist-info/top_level.txt
pywellcad-0.5.0.dist-info/RECORD
