Metadata-Version: 2.1
Name: pywellcad
Version: 0.5.0
Summary: a Python client for the WellCAD Automation API
Home-page: https://www.alt.lu/
Author: Advanced Logic Technology
Author-email: support@alt.lu
License: BSD 3-Clause License
Classifier: Programming Language :: Python :: 3
Classifier: License :: OSI Approved :: BSD License
Requires-Python: >=3.6
License-File: LICENSE.txt
Requires-Dist: pywin32 ==303 ; platform_system == "Windows"
